snail_core/__init__.py
snail_core/auth.py
snail_core/cli.py
snail_core/config.py
snail_core/core.py
snail_core/host_id.py
snail_core/uploader.py
snail_core/collectors/__init__.py
snail_core/collectors/base.py
snail_core/collectors/filesystem.py
snail_core/collectors/hardware.py
snail_core/collectors/logs.py
snail_core/collectors/network.py
snail_core/collectors/packages.py
snail_core/collectors/security.py
snail_core/collectors/services.py
snail_core/collectors/system.py
snail_core-0.5.4.dist-info/licenses/LICENSE
snail_core-0.5.4.dist-info/METADATA
snail_core-0.5.4.dist-info/WHEEL
snail_core-0.5.4.dist-info/entry_points.txt
snail_core-0.5.4.dist-info/top_level.txt
snail_core-0.5.4.dist-info/RECORD
